main.py
public_routes.py
config/database.py
controllers/auth.py
controllers/items.py
models/items.py
models/users.py
repositories/get_all.py
repositories/get_by_column.py
repositories/post.py
routes/auth.py
routes/items.py
security/verify_jwt_token.py
fastapi_mvc_boilerplate-0.1.0.dist-info/METADATA
fastapi_mvc_boilerplate-0.1.0.dist-info/WHEEL
fastapi_mvc_boilerplate-0.1.0.dist-info/top_level.txt
fastapi_mvc_boilerplate-0.1.0.dist-info/RECORD
