Metadata-Version: 2.4
Name: fastapi-mvc-boilerplate
Version: 0.1.0
Summary: Add your description here
Requires-Python: >=3.13
Requires-Dist: fastapi>=0.116.1
Requires-Dist: passlib[all]>=1.7.4
Requires-Dist: python-decouple>=3.8
Requires-Dist: python-jose>=3.5.0
Requires-Dist: sqlmodel>=0.0.24
Requires-Dist: uvicorn>=0.35.0
